{
  "bill_type": "BILL",
  "bill_number": "H.R.1381",
  "bill_url": "https://www.congress.gov/bill/119th-congress/house-bill/1381?s=1&r=213",
  "all_actions_url": "https://www.congress.gov/bill/119th-congress/house-bill/1381?s=1&r=213/all-actions",
  "congress": "\u2014 119th Congress (2025-2026)",
  "title": "To prohibit Federal funds from being made available to entities that refuse to provide treatment based on COVID19 vaccination status.",
  "sponsor_info": "Sponsor: Houchin, Erin [Rep.-R-IN-9] (Introduced 02/14/2025) Cosponsors: ( 2 )",
  "sponsor_name": "Houchin, Erin [Rep.-R-IN-9]",
  "sponsor_url": "https://www.congress.gov/member/erin-houchin/H001093",
  "cosponsors_count": "2",
  "cosponsors_url": "https://www.congress.gov/bill/119th-congress/house-bill/1381/cosponsors?s=1&r=213&overview=closed#tabs",
  "committees": "House - Energy and Commerce; Ways and Means",
  "latest_action": "House - 02/14/2025 Referred to the Committee on Energy and Commerce, and in addition to the Committee on Ways and Means, for a period to be subsequently determined by the Speaker, in each case for consideration of such provisions as fall within the jurisdiction of the committee... ( All Actions )",
  "latest_action_date": "02/14/2025",
  "status": "This bill has the status Introduced",
  "actions": []
}