{
  "bill_type": "BILL",
  "bill_number": "H.R.1330",
  "bill_url": "https://www.congress.gov/bill/119th-congress/house-bill/1330?s=1&r=265",
  "all_actions_url": "https://www.congress.gov/bill/119th-congress/house-bill/1330?s=1&r=265/all-actions",
  "congress": "\u2014 119th Congress (2025-2026)",
  "title": "To permit the Smithsonian National Museum of the American Latino to be located within the Reserve of the National Mall, and for other purposes.",
  "sponsor_info": "Sponsor: Malliotakis, Nicole [Rep.-R-NY-11] (Introduced 02/13/2025) Cosponsors: ( 51 )",
  "sponsor_name": "Malliotakis, Nicole [Rep.-R-NY-11]",
  "sponsor_url": "https://www.congress.gov/member/nicole-malliotakis/M000317",
  "cosponsors_count": "51",
  "cosponsors_url": "https://www.congress.gov/bill/119th-congress/house-bill/1330/cosponsors?s=1&r=265&overview=closed#tabs",
  "committees": "House - House Administration; Natural Resources",
  "latest_action": "House - 02/13/2025 Referred to the Committee on House Administration, and in addition to the Committee on Natural Resources, for a period to be subsequently determined by the Speaker, in each case for consideration of such provisions as fall within the jurisdiction of the committee... ( All Actions )",
  "latest_action_date": "02/13/2025",
  "status": "This bill has the status Introduced",
  "actions": []
}